huddle01/__init__.py
huddle01/__version__.py
huddle01/access_token.py
huddle01/active_speaker.py
huddle01/async_manager.py
huddle01/bot.py
huddle01/emitter.py
huddle01/handlers/__init__.py
huddle01/handlers/local_peer_handler.py
huddle01/handlers/remote_peer_handler.py
huddle01/handlers/room_handler.py
huddle01/handlers/socket_handler.py
huddle01/huddle_client.py
huddle01/local_peer.py
huddle01/log.py
huddle01/permissions.py
huddle01/proto/client/app_data_pb2.py
huddle01/proto/client/app_data_pb2.pyi
huddle01/proto/client/permissions_pb2.py
huddle01/proto/client/permissions_pb2.pyi
huddle01/proto/client/request_pb2.py
huddle01/proto/client/request_pb2.pyi
huddle01/proto/client/response_pb2.py
huddle01/proto/client/response_pb2.pyi
huddle01/proto/client/room_control_pb2.py
huddle01/proto/client/room_control_pb2.pyi
huddle01/proto/rtc/cascading_pb2.py
huddle01/proto/rtc/cascading_pb2.pyi
huddle01/proto/rtc/rtp_capabilities_pb2.py
huddle01/proto/rtc/rtp_capabilities_pb2.pyi
huddle01/proto/rtc/rtp_parameters_pb2.py
huddle01/proto/rtc/rtp_parameters_pb2.pyi
huddle01/proto/rtc/sctp_capabilities_pb2.py
huddle01/proto/rtc/sctp_capabilities_pb2.pyi
huddle01/proto/rtc/sctp_stream_parameters_pb2.py
huddle01/proto/rtc/sctp_stream_parameters_pb2.pyi
huddle01/proto/rtc/sdp_info_pb2.py
huddle01/proto/rtc/sdp_info_pb2.pyi
huddle01/remote_peer.py
huddle01/room.py
huddle01/socket.py
huddle01/utils.py
huddle01-1.1.2.dist-info/METADATA
huddle01-1.1.2.dist-info/WHEEL
huddle01-1.1.2.dist-info/entry_points.txt
huddle01-1.1.2.dist-info/RECORD
