Metadata-Version: 2.1
Name: huddle01
Version: 1.1.2
Summary: Python Real-Time-SDK for Huddle01 dRTC Network
License: BSD-3-Clause
Keywords: huddle01,video,conferencing
Author: Om Gupta
Author-email: omgupta0720@gmail.com
Maintainer: Om Gupta
Maintainer-email: omgupta0720@gmail.com
Requires-Python: >=3.12,<4.0
Classifier: License :: OSI Approved :: BSD License
Classifier: Programming Language :: Python :: 3
Classifier: Programming Language :: Python :: 3.12
Requires-Dist: aiohttp (>=3.11.16,<4.0.0)
Requires-Dist: asyncio (>=3.4.3,<4.0.0)
Requires-Dist: huddle01-pymediasoup (>=1.2.1,<2.0.0)
Requires-Dist: protobuf (>=5.28.2,<6.0.0)
Requires-Dist: pydantic (>=1.10.17,<3.0.0)
Requires-Dist: pyee (==11.1.0)
Requires-Dist: python-dotenv (>=1.0.1,<2.0.0)
Requires-Dist: ruff (>=0.6.0,<=0.9.1)
Requires-Dist: websockets (>=13.1,<14.0)
